ppauth-0.1.10.dist-info/METADATA
ppauth-0.1.10.dist-info/WHEEL
ppauth-0.1.10.dist-info/entry_points.txt
ppauth.libs/libcrypto-8bcb947c.so.3
ppauth.libs/libssl-9e2b5710.so.3
ppauth/__init__.py
ppauth/ppauth.abi3.so
ppauth-0.1.10.dist-info/RECORD
